LICENSE
MANIFEST.in
Makefile
README
TODO
ez_setup.py
setup.cfg
setup.py
.hg/store/data/lib/blogengine2/json__views/admin/____init____.py.i
.hg/store/data/lib/blogengine2/json__views/admin/add.py.i
.hg/store/data/lib/blogengine2/json__views/admin/delete.py.i
.hg/store/data/lib/blogengine2/json__views/admin/edit.py.i
.hg/store/data/lib/blogengine2/views/admin/____init____.py.i
.hg/store/data/lib/blogengine2/views/admin/add.py.i
.hg/store/data/lib/blogengine2/views/admin/delete.py.i
.hg/store/data/lib/blogengine2/views/admin/edit.py.i
docs/blogengine-notes.txt
docs/schevo-initdb.txt
docs/www/index.rst
lib/blogengine2/__init__.py
lib/blogengine2/config.py
lib/blogengine2/urls.py
lib/blogengine2.egg-info/PKG-INFO
lib/blogengine2.egg-info/SOURCES.txt
lib/blogengine2.egg-info/dependency_links.txt
lib/blogengine2.egg-info/requires.txt
lib/blogengine2.egg-info/top_level.txt
lib/blogengine2.egg-info/zip-safe
lib/blogengine2/contrib/__init__.py
lib/blogengine2/contrib/addthis/__init__.py
lib/blogengine2/contrib/addthis/context_processors.py
lib/blogengine2/contrib/api_v1/__init__.py
lib/blogengine2/contrib/api_v1/actions.py
lib/blogengine2/contrib/api_v1/comment.py
lib/blogengine2/contrib/api_v1/email.py
lib/blogengine2/contrib/api_v1/model.py
lib/blogengine2/contrib/api_v1/forms/__init__.py
lib/blogengine2/contrib/api_v1/forms/widgets/__init__.py
lib/blogengine2/contrib/api_v1/forms/widgets/autocomplete.py
lib/blogengine2/contrib/blog/__init__.py
lib/blogengine2/contrib/blog/urls.py
lib/blogengine2/contrib/blog/views/__init__.py
lib/blogengine2/contrib/blog/views/detail.py
lib/blogengine2/contrib/blog/views/index.py
lib/blogengine2/contrib/blog/views/rss.py
lib/blogengine2/contrib/comments/__init__.py
lib/blogengine2/contrib/comments/forms.py
lib/blogengine2/contrib/comments/signals.py
lib/blogengine2/contrib/comments/urls.py
lib/blogengine2/contrib/comments/views.py
lib/blogengine2/contrib/i18n/__init__.py
lib/blogengine2/contrib/messages/__init__.py
lib/blogengine2/contrib/messages/forms.py
lib/blogengine2/contrib/messages/urls.py
lib/blogengine2/contrib/messages/views.py
lib/blogengine2/contrib/poll/__init__.py
lib/blogengine2/contrib/poll/model.py
lib/blogengine2/contrib/poll/urls.py
