Metadata-Version: 1.2
Name: blogengine2
Version: 0.9.8
Summary: Python-powered microblogging API
Home-page: https://www.isotopesoftware.ca/software/blogengine2/
Author: Etienne Robillard
Author-email: tkadm30@yandex.com
Maintainer: Etienne Robillard
Maintainer-email: tkadm30@yandex.com
License: Apache
Keywords: BlogEngine2 django-hotsauce
Platform: UNKNOWN
